{"id":"33de5f9e-621e-43e2-b7ad-205badad9acb","alder":"1 - 5","ansatte":{"antallFra":20,"antallTil":24},"eierform":"Privat","basilId":"52097","erAktiv":true,"erBarnehage":true,"erBarnehageEier":false,"erPrivatBarnehage":true,"fylke":{"fylkesnavn":"Sør-Trøndelag","fylkesnummer":"16"},"kommune":{"kommunenavn":"Trondheim","kommunenummer":"1601"},"kontaktinformasjon":{"postAdresse":{"adresselinje":"Anders Søyseths Veg 26","postnr":"7056","poststed":"RANHEIM"},"besoksAdresse":{"adresselinje":"Anders Søyseths Veg 26","postnr":"7056","poststed":"RANHEIM"},"epost":"dl.grilstad@bhg.no","url":"","telefon":""},"koordinatLatLng":[63.43043,10.50711],"malform":{"malformType":"B","malformNavn":"Bokmål"},"opprettetDato":"1/19/2007","navn":"Grilstad Fus barnehage AS","orgnr":"990894426","nsrId":"1021587","indikatorDataBarnehage":{"antallBarn":90,"antallBarnPerAnsatt":6.4,"andelAnsatteMedBarneOgUngdomsarbeiderfag":33.3,"andelAnsatteMedAnnenPedagogiskUtdanning":null,"andelAnsatteBarnehagelarer":47.6,"andelAnsatteMedAnnenBakgrunn":19.0,"andelAnsatteMedPedagogiskUtdanning":null,"lekeOgOppholdsarealPerBarn":4.5,"andelBarnehagerSomOppfyllerPedagognormen":null,"andelBarnehagerSomIkkeOppfyllerPedagognormen":null,"andelBarnehagerSomOppfyllerPedagognormenMedDispensasjon":null},"indikatorDataKommune":{"antallBarn":10746,"antallBarnPerAnsatt":6.2,"andelAnsatteMedBarneOgUngdomsarbeiderfag":17.7,"andelAnsatteMedAnnenPedagogiskUtdanning":null,"andelAnsatteBarnehagelarer":47.7,"andelAnsatteMedAnnenBakgrunn":34.6,"andelAnsatteMedPedagogiskUtdanning":null,"lekeOgOppholdsarealPerBarn":4.8,"andelBarnehagerSomOppfyllerPedagognormen":82.9,"andelBarnehagerSomIkkeOppfyllerPedagognormen":16.6,"andelBarnehagerSomOppfyllerPedagognormenMedDispensasjon":0.5},"kostpenger":300.0,"type":"Ordinær barnehage","pedagogiskProfil":null,"apningstidFra":"06:45","apningstidTil":"17:15","oppfyllerPedagognorm":"Oppfyller normen","totalAntallKvadratmeter":404.8,"urlTilSoknadOmBarnehageplass":"http://www.trondheim.kommune.no/barnehage/#"}