{"id":"f37a8ada-c991-4c9d-833d-74ebc0ffd22d","alder":"1 - 2","ansatte":{"antallFra":1,"antallTil":4},"eierform":"Privat","basilId":"48874","erAktiv":true,"erBarnehage":true,"erBarnehageEier":false,"erPrivatBarnehage":true,"fylke":{"fylkesnavn":"Sør-Trøndelag","fylkesnummer":"16"},"kommune":{"kommunenavn":"Trondheim","kommunenummer":"1601"},"kontaktinformasjon":{"postAdresse":{"adresselinje":"Brudalsvegen 17e","postnr":"7088","poststed":"HEIMDAL"},"besoksAdresse":{"adresselinje":"Brudalsvegen 17e","postnr":"7088","poststed":"HEIMDAL"},"epost":"annirensolberg1@gmail.com","url":"","telefon":"99402230"},"koordinatLatLng":[63.35878,10.3589],"malform":{"malformType":"B","malformNavn":"Bokmål"},"opprettetDato":"8/12/2002","navn":"Brudalstunet Familiebarnehage","orgnr":"984736525","nsrId":"1020831","indikatorDataBarnehage":{"antallBarn":4,"antallBarnPerAnsatt":null,"andelAnsatteMedBarneOgUngdomsarbeiderfag":null,"andelAnsatteMedAnnenPedagogiskUtdanning":null,"andelAnsatteBarnehagelarer":null,"andelAnsatteMedAnnenBakgrunn":null,"andelAnsatteMedPedagogiskUtdanning":null,"lekeOgOppholdsarealPerBarn":null,"andelBarnehagerSomOppfyllerPedagognormen":null,"andelBarnehagerSomIkkeOppfyllerPedagognormen":null,"andelBarnehagerSomOppfyllerPedagognormenMedDispensasjon":null},"indikatorDataKommune":{"antallBarn":10746,"antallBarnPerAnsatt":6.2,"andelAnsatteMedBarneOgUngdomsarbeiderfag":17.7,"andelAnsatteMedAnnenPedagogiskUtdanning":10.2,"andelAnsatteBarnehagelarer":47.7,"andelAnsatteMedAnnenBakgrunn":24.5,"andelAnsatteMedPedagogiskUtdanning":57.8,"lekeOgOppholdsarealPerBarn":4.8,"andelBarnehagerSomOppfyllerPedagognormen":82.9,"andelBarnehagerSomIkkeOppfyllerPedagognormen":16.6,"andelBarnehagerSomOppfyllerPedagognormenMedDispensasjon":0.5},"kostpenger":0.0,"type":"Familiebarnehage","pedagogiskProfil":null,"apningstidFra":"07:30","apningstidTil":"16:15","oppfyllerPedagognorm":"","totalAntallKvadratmeter":null,"urlTilSoknadOmBarnehageplass":"http://www.trondheim.kommune.no/barnehage/#"}