{"id":"88c2d53e-f4b0-472d-bb73-12f922475537","alder":"1 - 5","ansatte":{"antallFra":1,"antallTil":4},"eierform":"Privat","basilId":"49276","erAktiv":true,"erBarnehage":true,"erBarnehageEier":false,"erPrivatBarnehage":true,"fylke":{"fylkesnavn":"Østfold","fylkesnummer":"01"},"kommune":{"kommunenavn":"Fredrikstad","kommunenummer":"0106"},"kontaktinformasjon":{"postAdresse":{"adresselinje":"Mølleveien 4","postnr":"1613","poststed":"FREDRIKSTAD"},"besoksAdresse":{"adresselinje":"Mølleveien 4","postnr":"1613","poststed":"FREDRIKSTAD"},"epost":"anne_marit74@hotmail.com","url":"","telefon":""},"koordinatLatLng":[59.22701,10.9217],"malform":{"malformType":"B","malformNavn":"Bokmål"},"opprettetDato":"1/1/2009","navn":"Trosvikhaven Familiebarnehage","orgnr":"995078651","nsrId":"1021211","indikatorDataBarnehage":{"antallBarn":4,"antallBarnPerAnsatt":null,"andelAnsatteMedBarneOgUngdomsarbeiderfag":null,"andelAnsatteMedAnnenPedagogiskUtdanning":null,"andelAnsatteBarnehagelarer":null,"andelAnsatteMedAnnenBakgrunn":null,"andelAnsatteMedPedagogiskUtdanning":null,"lekeOgOppholdsarealPerBarn":null,"andelBarnehagerSomOppfyllerPedagognormen":null,"andelBarnehagerSomIkkeOppfyllerPedagognormen":null,"andelBarnehagerSomOppfyllerPedagognormenMedDispensasjon":null},"indikatorDataKommune":{"antallBarn":3861,"antallBarnPerAnsatt":6.3,"andelAnsatteMedBarneOgUngdomsarbeiderfag":19.1,"andelAnsatteMedAnnenPedagogiskUtdanning":null,"andelAnsatteBarnehagelarer":44.3,"andelAnsatteMedAnnenBakgrunn":36.7,"andelAnsatteMedPedagogiskUtdanning":null,"lekeOgOppholdsarealPerBarn":5.4,"andelBarnehagerSomOppfyllerPedagognormen":93.7,"andelBarnehagerSomIkkeOppfyllerPedagognormen":4.8,"andelBarnehagerSomOppfyllerPedagognormenMedDispensasjon":1.6},"kostpenger":250.0,"type":"Familiebarnehage","pedagogiskProfil":null,"apningstidFra":"07:15","apningstidTil":"16:15","oppfyllerPedagognorm":"","totalAntallKvadratmeter":null,"urlTilSoknadOmBarnehageplass":"https://www.fredrikstad.kommune.no/no/Tjenester/Barn-og-familie/Barnehage/Sok-om-barnehageplass/#"}