{
    "type": "FeatureCollection",
    "features": [
        {
            "type": "Feature",
            "id": "node/-3419",
            "properties": {
                "amenity": "kindergarten",
                "capacity": "83",
                "contact:email": "julebygda@laringsverkstedet.no",
                "contact:phone": "97997220",
                "contact:website": "http://www.laringsverkstedet.no/julebygda",
                "max_age": "5",
                "min_age": "1",
                "name": "Læringsverkstedet barnehage Avd Julebygda",
                "no-barnehage:nsrid": "1015070",
                "operator": "Læringsverkstedet AS",
                "operator:type": "private",
                "start_date": "2012-01-01",
                "id": "node/-3419"
            },
            "geometry": {
                "type": "Point",
                "coordinates": [
                    5.6578,
                    58.8319
                ]
            }
        }
    ]
}