{
    "type": "FeatureCollection",
    "features": [
        {
            "type": "Feature",
            "id": "node/-3414",
            "properties": {
                "amenity": "kindergarten",
                "contact:phone": "51 68 82 36",
                "name": "Knøttene Åpen barnehage",
                "no-barnehage:nsrid": "1015878",
                "operator": "Sandnes Kirkelige Fellesråd",
                "operator:type": "private",
                "start_date": "2000-01-01",
                "id": "node/-3414"
            },
            "geometry": {
                "type": "Point",
                "coordinates": [
                    5.85494,
                    58.9278
                ]
            }
        },
        {
            "type": "Feature",
            "id": "node/-3408",
            "properties": {
                "amenity": "kindergarten",
                "capacity": "57",
                "contact:phone": "51 68 88 75",
                "max_age": "5",
                "min_age": "1",
                "name": "Hommersåk barnehage",
                "no-barnehage:nsrid": "1012888",
                "operator": "Sandnes kommune",
                "operator:type": "public",
                "start_date": "1989-01-01",
                "id": "node/-3408"
            },
            "geometry": {
                "type": "Point",
                "coordinates": [
                    5.84809,
                    58.9276
                ]
            }
        }
    ]
}