{
    "type": "FeatureCollection",
    "features": [
        {
            "type": "Feature",
            "id": "node/-4193",
            "properties": {
                "amenity": "kindergarten",
                "capacity": "28",
                "max_age": "5",
                "min_age": "1",
                "name": "Sekse barnehage",
                "no-barnehage:nsrid": "1018114",
                "operator": "Ullensvang Herad",
                "operator:type": "public",
                "start_date": "1989-01-01",
                "id": "node/-4193"
            },
            "geometry": {
                "type": "Point",
                "coordinates": [
                    6.62062,
                    60.2518
                ]
            }
        }
    ]
}