{
    "type": "FeatureCollection",
    "features": [
        {
            "type": "Feature",
            "id": "node/-5700",
            "properties": {
                "amenity": "kindergarten",
                "capacity": "24",
                "max_age": "5",
                "min_age": "1",
                "name": "Skutvik Oppvekstsenter Avd Barnehage",
                "no-barnehage:nsrid": "1013678",
                "operator": "Hamarøy kommune",
                "operator:type": "public",
                "start_date": "1989-01-01",
                "id": "node/-5700"
            },
            "geometry": {
                "type": "Point",
                "coordinates": [
                    15.3276,
                    68.0168
                ]
            }
        }
    ]
}