{
    "type": "FeatureCollection",
    "features": [
        {
            "type": "Feature",
            "id": "node/-6107",
            "properties": {
                "amenity": "kindergarten",
                "capacity": "24",
                "contact:email": "oksfjord.barnehage@loppa.kommune.no",
                "contact:phone": "78 45 31 40",
                "max_age": "5",
                "min_age": "1",
                "name": "Øksfjord barnehage",
                "no-barnehage:nsrid": "1013723",
                "operator": "Loppa kommune",
                "operator:type": "public",
                "start_date": "1989-01-01",
                "id": "node/-6107"
            },
            "geometry": {
                "type": "Point",
                "coordinates": [
                    22.3481,
                    70.2471
                ]
            }
        }
    ]
}