{"id":"e63edba0-cf5d-4644-b50e-f3daee575f83","alder":"1 - 5","ansatte":{"antallFra":15,"antallTil":19},"eierform":"Privat","basilId":"47680","erAktiv":true,"erBarnehage":true,"erBarnehageEier":false,"erPrivatBarnehage":true,"fylke":{"fylkesnavn":"Oppland","fylkesnummer":"05"},"kommune":{"kommunenavn":"Gjøvik","kommunenummer":"0502"},"kontaktinformasjon":{"postAdresse":{"adresselinje":"Gjennomfaret 2","postnr":"2818","poststed":"GJØVIK"},"besoksAdresse":{"adresselinje":"Gjennomfaret 2","postnr":"2818","poststed":"GJØVIK"},"epost":"","url":"","telefon":""},"koordinatLatLng":[60.7737,10.6695],"malform":{"malformType":"B","malformNavn":"Bokmål"},"opprettetDato":"1/2/1989","navn":"Engehaugen Menighetsbarnehage","orgnr":"973456458","nsrId":"1015571","indikatorDataBarnehage":{"antallBarn":37,"antallBarnPerAnsatt":5.7,"andelAnsatteMedBarneOgUngdomsarbeiderfag":0.0,"andelAnsatteMedAnnenPedagogiskUtdanning":9.1,"andelAnsatteBarnehagelarer":36.4,"andelAnsatteMedAnnenBakgrunn":54.5,"andelAnsatteMedPedagogiskUtdanning":45.5,"lekeOgOppholdsarealPerBarn":6.9},"indikatorDataKommune":{"antallBarn":1501,"antallBarnPerAnsatt":6.2,"andelAnsatteMedBarneOgUngdomsarbeiderfag":19.2,"andelAnsatteMedAnnenPedagogiskUtdanning":3.9,"andelAnsatteBarnehagelarer":44.8,"andelAnsatteMedAnnenBakgrunn":32.1,"andelAnsatteMedPedagogiskUtdanning":48.7,"lekeOgOppholdsarealPerBarn":5.7},"kostpenger":325.0,"type":"Ordinær barnehage","pedagogiskProfil":"Tros- eller livssynsbarnehage","apningstidFra":"07:00","apningstidTil":"16:30","oppfyllerPedagognorm":"Oppfyller normen med dispensasjon fra utdanningskravet","urlTilSoknadOmBarnehageplass":"http://www.gjovik.kommune.no/barnehage/samordnet-opptak/#"}