{"id":"fc34ab96-e887-42b6-bc22-233e6410949d","alder":"1 - 5","ansatte":{"antallFra":20,"antallTil":24},"eierform":"Privat","basilId":"48967","erAktiv":true,"erBarnehage":true,"erBarnehageEier":false,"erPrivatBarnehage":true,"fylke":{"fylkesnavn":"Sør-Trøndelag","fylkesnummer":"16"},"kommune":{"kommunenavn":"Malvik","kommunenummer":"1663"},"kontaktinformasjon":{"postAdresse":{"adresselinje":"Svebergvegen 8","postnr":"7550","poststed":"HOMMELVIK"},"besoksAdresse":{"adresselinje":"Svebergvegen 8","postnr":"7550","poststed":"HOMMELVIK"},"epost":"","url":"","telefon":"73 97 31 90"},"koordinatLatLng":[63.42195,10.74975],"malform":{"malformType":"B","malformNavn":"Bokmål"},"opprettetDato":"5/29/2002","navn":"Sveberg barnehage Sa","orgnr":"984569742","nsrId":"1020803","indikatorDataBarnehage":{"antallBarn":64,"antallBarnPerAnsatt":6.6,"andelAnsatteMedBarneOgUngdomsarbeiderfag":13.3,"andelAnsatteMedAnnenPedagogiskUtdanning":0.0,"andelAnsatteBarnehagelarer":46.7,"andelAnsatteMedAnnenBakgrunn":40.0,"andelAnsatteMedPedagogiskUtdanning":46.7,"lekeOgOppholdsarealPerBarn":4.3},"indikatorDataKommune":{"antallBarn":745,"antallBarnPerAnsatt":6.1,"andelAnsatteMedBarneOgUngdomsarbeiderfag":14.8,"andelAnsatteMedAnnenPedagogiskUtdanning":0.0,"andelAnsatteBarnehagelarer":44.0,"andelAnsatteMedAnnenBakgrunn":41.2,"andelAnsatteMedPedagogiskUtdanning":44.0,"lekeOgOppholdsarealPerBarn":5.5},"kostpenger":300.0,"type":"Ordinær barnehage","pedagogiskProfil":"","apningstidFra":"06:45","apningstidTil":"17:00","oppfyllerPedagognorm":"Oppfyller normen","urlTilSoknadOmBarnehageplass":"http://www.malvik.kommune.no/barnehager.163746.no.html#"}