{"id":"c64ffa8b-a6d1-4deb-8a35-9edd3a2b3189","alder":"1 - 5","ansatte":{"antallFra":10,"antallTil":14},"eierform":"Kommunal","basilId":"51224","erAktiv":true,"erBarnehage":true,"erBarnehageEier":false,"erPrivatBarnehage":false,"fylke":{"fylkesnavn":"Nord-Trøndelag","fylkesnummer":"17"},"kommune":{"kommunenavn":"Stjørdal","kommunenummer":"1714"},"kontaktinformasjon":{"postAdresse":{"adresselinje":"","postnr":"7520","poststed":"HEGRA"},"besoksAdresse":{"adresselinje":"","postnr":"7520","poststed":"HEGRA"},"epost":"","url":"","telefon":""},"koordinatLatLng":[63.4639,11.1143],"malform":{"malformType":"B","malformNavn":"Bokmål"},"opprettetDato":"1/1/1989","navn":"Skjelstadmark Oppvekstsenter Avd Skjelstadmark Barnehage","orgnr":"975311856","nsrId":"1018267","indikatorDataBarnehage":{"antallBarn":34,"antallBarnPerAnsatt":6.0,"andelAnsatteMedBarneOgUngdomsarbeiderfag":33.3,"andelAnsatteMedAnnenPedagogiskUtdanning":22.2,"andelAnsatteBarnehagelarer":44.4,"andelAnsatteMedAnnenBakgrunn":0.0,"andelAnsatteMedPedagogiskUtdanning":66.7,"lekeOgOppholdsarealPerBarn":4.3},"indikatorDataKommune":{"antallBarn":1391,"antallBarnPerAnsatt":6.4,"andelAnsatteMedBarneOgUngdomsarbeiderfag":18.9,"andelAnsatteMedAnnenPedagogiskUtdanning":1.6,"andelAnsatteBarnehagelarer":44.0,"andelAnsatteMedAnnenBakgrunn":35.5,"andelAnsatteMedPedagogiskUtdanning":45.6,"lekeOgOppholdsarealPerBarn":5.1},"kostpenger":400.0,"type":"Ordinær barnehage","pedagogiskProfil":"","apningstidFra":"06:45","apningstidTil":"16:30","oppfyllerPedagognorm":"Oppfyller ikke normen","urlTilSoknadOmBarnehageplass":"https://www.stjordal.kommune.no/barn-og-familie/Sider/default.aspx#"}