{"id":"0c0d4fdb-2579-4808-bf42-4e5731477b03","alder":"1 - 5","ansatte":{"antallFra":15,"antallTil":19},"eierform":"Kommunal","basilId":"50647","erAktiv":true,"erBarnehage":true,"erBarnehageEier":false,"erPrivatBarnehage":false,"fylke":{"fylkesnavn":"Nord-Trøndelag","fylkesnummer":"17"},"kommune":{"kommunenavn":"Stjørdal","kommunenummer":"1714"},"kontaktinformasjon":{"postAdresse":{"adresselinje":"Nordregata 14","postnr":"7504","poststed":"STJØRDAL"},"besoksAdresse":{"adresselinje":"Nordregata 14","postnr":"7504","poststed":"STJØRDAL"},"epost":"solunn.almli@stjordal.kommune.no","url":"","telefon":""},"koordinatLatLng":[63.4711,10.9197],"malform":{"malformType":"B","malformNavn":"Bokmål"},"opprettetDato":"1/1/1976","navn":"Midtheim barnehage","orgnr":"975296105","nsrId":"1017374","indikatorDataBarnehage":{"antallBarn":50,"antallBarnPerAnsatt":6.2,"andelAnsatteMedBarneOgUngdomsarbeiderfag":33.3,"andelAnsatteMedAnnenPedagogiskUtdanning":8.3,"andelAnsatteBarnehagelarer":50.0,"andelAnsatteMedAnnenBakgrunn":8.3,"andelAnsatteMedPedagogiskUtdanning":58.3,"lekeOgOppholdsarealPerBarn":4.6,"andelBarnehagerSomOppfyllerPedagognormen":null,"andelBarnehagerSomIkkeOppfyllerPedagognormen":null,"andelBarnehagerSomOppfyllerPedagognormenMedDispensasjon":null},"indikatorDataKommune":{"antallBarn":1379,"antallBarnPerAnsatt":6.1,"andelAnsatteMedBarneOgUngdomsarbeiderfag":20.4,"andelAnsatteMedAnnenPedagogiskUtdanning":7.6,"andelAnsatteBarnehagelarer":44.8,"andelAnsatteMedAnnenBakgrunn":27.2,"andelAnsatteMedPedagogiskUtdanning":52.4,"lekeOgOppholdsarealPerBarn":5.9,"andelBarnehagerSomOppfyllerPedagognormen":85.2,"andelBarnehagerSomIkkeOppfyllerPedagognormen":14.8,"andelBarnehagerSomOppfyllerPedagognormenMedDispensasjon":0.0},"kostpenger":400.0,"type":"Ordinær barnehage","pedagogiskProfil":["Miljøbarnehage"],"apningstidFra":"07:00","apningstidTil":"16:45","oppfyllerPedagognorm":"Oppfyller normen","totalAntallKvadratmeter":230.0,"urlTilSoknadOmBarnehageplass":"https://www.stjordal.kommune.no/barn-og-familie/Sider/default.aspx#"}