{"id":"9eb513c8-3813-4109-99e1-532e2e39282c","alder":"1 - 5","ansatte":{"antallFra":15,"antallTil":19},"eierform":"Kommunal","basilId":"50653","erAktiv":true,"erBarnehage":true,"erBarnehageEier":false,"erPrivatBarnehage":false,"fylke":{"fylkesnavn":"Finnmark","fylkesnummer":"20"},"kommune":{"kommunenavn":"Sør-Varanger","kommunenummer":"2030"},"kontaktinformasjon":{"postAdresse":{"adresselinje":"Kronprinsens Gate 14","postnr":"9900","poststed":"KIRKENES"},"besoksAdresse":{"adresselinje":"Kronprinsens Gate 14","postnr":"9900","poststed":"KIRKENES"},"epost":"ynpe@svk.no","url":"","telefon":"78991612"},"koordinatLatLng":[69.7222,30.0454],"malform":{"malformType":"B","malformNavn":"Bokmål"},"opprettetDato":"1/1/1976","navn":"Kirkenes barnehage","orgnr":"975296245","nsrId":"1017380","indikatorDataBarnehage":{"antallBarn":54,"antallBarnPerAnsatt":6.0,"andelAnsatteMedBarneOgUngdomsarbeiderfag":15.4,"andelAnsatteMedAnnenPedagogiskUtdanning":null,"andelAnsatteBarnehagelarer":38.5,"andelAnsatteMedAnnenBakgrunn":46.2,"andelAnsatteMedPedagogiskUtdanning":null,"lekeOgOppholdsarealPerBarn":10.1,"andelBarnehagerSomOppfyllerPedagognormen":null,"andelBarnehagerSomIkkeOppfyllerPedagognormen":null,"andelBarnehagerSomOppfyllerPedagognormenMedDispensasjon":null},"indikatorDataKommune":{"antallBarn":494,"antallBarnPerAnsatt":5.5,"andelAnsatteMedBarneOgUngdomsarbeiderfag":23.7,"andelAnsatteMedAnnenPedagogiskUtdanning":null,"andelAnsatteBarnehagelarer":37.8,"andelAnsatteMedAnnenBakgrunn":38.5,"andelAnsatteMedPedagogiskUtdanning":null,"lekeOgOppholdsarealPerBarn":8.0,"andelBarnehagerSomOppfyllerPedagognormen":50.0,"andelBarnehagerSomIkkeOppfyllerPedagognormen":7.1,"andelBarnehagerSomOppfyllerPedagognormenMedDispensasjon":42.9},"kostpenger":200.0,"type":"Ordinær barnehage","pedagogiskProfil":null,"apningstidFra":"07:15","apningstidTil":"16:15","oppfyllerPedagognorm":"Oppfyller normen","totalAntallKvadratmeter":548.0,"urlTilSoknadOmBarnehageplass":"http://www.sor-varanger.kommune.no/barnehageplass.5318590-17878.html#"}