{"id":"2a10c0fa-b5b1-4c1c-b20a-31dd9d8a16d0","alder":"1 - 5","ansatte":{"antallFra":25,"antallTil":29},"eierform":"Privat","basilId":"49381","erAktiv":true,"erBarnehage":true,"erBarnehageEier":false,"erPrivatBarnehage":true,"fylke":{"fylkesnavn":"Akershus","fylkesnummer":"02"},"kommune":{"kommunenavn":"Asker","kommunenummer":"0220"},"kontaktinformasjon":{"postAdresse":{"adresselinje":"Vollenveien 34","postnr":"1390","poststed":"VOLLEN"},"besoksAdresse":{"adresselinje":"Vollenveien 34","postnr":"1390","poststed":"VOLLEN"},"epost":"rektor@vollenmontessore.no","url":"http://www.vollenmontessori.no","telefon":"66 98 71 20"},"koordinatLatLng":[59.80526,10.4767],"malform":{"malformType":"B","malformNavn":"Bokmål"},"opprettetDato":"1/1/2006","navn":"Stiftelsen Vollen Montessori- barnehage","orgnr":"991746358","nsrId":"1020816","indikatorDataBarnehage":{"antallBarn":84,"antallBarnPerAnsatt":5.6,"andelAnsatteMedBarneOgUngdomsarbeiderfag":4.3,"andelAnsatteMedAnnenPedagogiskUtdanning":4.3,"andelAnsatteBarnehagelarer":13.0,"andelAnsatteMedAnnenBakgrunn":78.3,"andelAnsatteMedPedagogiskUtdanning":17.4,"lekeOgOppholdsarealPerBarn":4.7},"indikatorDataKommune":{"antallBarn":3531,"antallBarnPerAnsatt":6.0,"andelAnsatteMedBarneOgUngdomsarbeiderfag":17.3,"andelAnsatteMedAnnenPedagogiskUtdanning":5.9,"andelAnsatteBarnehagelarer":38.2,"andelAnsatteMedAnnenBakgrunn":38.6,"andelAnsatteMedPedagogiskUtdanning":44.1,"lekeOgOppholdsarealPerBarn":4.9},"kostpenger":360.0,"type":"Ordinær barnehage","pedagogiskProfil":"Montessoribarnehage","apningstidFra":"07:30","apningstidTil":"17:00","oppfyllerPedagognorm":"Oppfyller normen med dispensasjon fra utdanningskravet","urlTilSoknadOmBarnehageplass":"http://www.asker.kommune.no/Barnehage/#"}