{"id":"bddc58c6-f4e7-423a-b98c-2b9b9286a59e","alder":"1 - 5","ansatte":{"antallFra":15,"antallTil":19},"eierform":"Kommunal","basilId":"51795","erAktiv":true,"erBarnehage":true,"erBarnehageEier":false,"erPrivatBarnehage":false,"fylke":{"fylkesnavn":"Oslo","fylkesnummer":"03"},"kommune":{"kommunenavn":"Oslo","kommunenummer":"0301"},"kontaktinformasjon":{"postAdresse":{"adresselinje":"Ammerudhellinga 2-4","postnr":"0959","poststed":"OSLO"},"besoksAdresse":{"adresselinje":"Ammerudhellinga 2-4","postnr":"0959","poststed":"OSLO"},"epost":"anne.helen.gusland@bgr.oslo.kommune.no","url":"","telefon":""},"koordinatLatLng":[59.9603,10.8661],"malform":{"malformType":"B","malformNavn":"Bokmål"},"opprettetDato":"1/20/1998","navn":"Tjernveien barnehage","orgnr":"979591942","nsrId":"1015631","indikatorDataBarnehage":{"antallBarn":54,"antallBarnPerAnsatt":6.0,"andelAnsatteMedBarneOgUngdomsarbeiderfag":15.4,"andelAnsatteMedAnnenPedagogiskUtdanning":null,"andelAnsatteBarnehagelarer":38.5,"andelAnsatteMedAnnenBakgrunn":46.2,"andelAnsatteMedPedagogiskUtdanning":null,"lekeOgOppholdsarealPerBarn":4.4,"andelBarnehagerSomOppfyllerPedagognormen":null,"andelBarnehagerSomIkkeOppfyllerPedagognormen":null,"andelBarnehagerSomOppfyllerPedagognormenMedDispensasjon":null},"indikatorDataKommune":{"antallBarn":null,"antallBarnPerAnsatt":6.0,"andelAnsatteMedBarneOgUngdomsarbeiderfag":8.7,"andelAnsatteMedAnnenPedagogiskUtdanning":null,"andelAnsatteBarnehagelarer":36.1,"andelAnsatteMedAnnenBakgrunn":55.3,"andelAnsatteMedPedagogiskUtdanning":null,"lekeOgOppholdsarealPerBarn":5.2,"andelBarnehagerSomOppfyllerPedagognormen":56.5,"andelBarnehagerSomIkkeOppfyllerPedagognormen":6.0,"andelBarnehagerSomOppfyllerPedagognormenMedDispensasjon":37.5},"kostpenger":112.0,"type":"Ordinær barnehage","pedagogiskProfil":null,"apningstidFra":"07:30","apningstidTil":"17:00","oppfyllerPedagognorm":"Oppfyller normen","totalAntallKvadratmeter":238.0,"urlTilSoknadOmBarnehageplass":"https://www.oslo.kommune.no/barnehage/soke-eller-bytte-barnehage/"}