{"id":"f5d92fc3-6e68-4bc9-8dee-e4498842f958","alder":"1 - 5","ansatte":{"antallFra":45,"antallTil":49},"eierform":"Kommunal","basilId":"50549","erAktiv":true,"erBarnehage":true,"erBarnehageEier":false,"erPrivatBarnehage":false,"fylke":{"fylkesnavn":"Oslo","fylkesnummer":"03"},"kommune":{"kommunenavn":"Oslo","kommunenummer":"0301"},"kontaktinformasjon":{"postAdresse":{"adresselinje":"Ammerudhellinga 49","postnr":"0959","poststed":"OSLO"},"besoksAdresse":{"adresselinje":"Ammerudhellinga 49","postnr":"0959","poststed":"OSLO"},"epost":"astrid.korsvold@bgr.oslo.kommune.no","url":"","telefon":""},"koordinatLatLng":[59.9626,10.8781],"malform":{"malformType":"B","malformNavn":"Bokmål"},"opprettetDato":"12/29/1971","navn":"Ammerudlia barnehage","orgnr":"975291278","nsrId":"1017278","indikatorDataBarnehage":{"antallBarn":135,"antallBarnPerAnsatt":6.0,"andelAnsatteMedBarneOgUngdomsarbeiderfag":9.7,"andelAnsatteMedAnnenPedagogiskUtdanning":16.1,"andelAnsatteBarnehagelarer":25.8,"andelAnsatteMedAnnenBakgrunn":48.4,"andelAnsatteMedPedagogiskUtdanning":41.9,"lekeOgOppholdsarealPerBarn":5.1,"andelBarnehagerSomOppfyllerPedagognormen":null,"andelBarnehagerSomIkkeOppfyllerPedagognormen":null,"andelBarnehagerSomOppfyllerPedagognormenMedDispensasjon":null},"indikatorDataKommune":{"antallBarn":null,"antallBarnPerAnsatt":6.0,"andelAnsatteMedBarneOgUngdomsarbeiderfag":8.7,"andelAnsatteMedAnnenPedagogiskUtdanning":12.3,"andelAnsatteBarnehagelarer":36.1,"andelAnsatteMedAnnenBakgrunn":43.0,"andelAnsatteMedPedagogiskUtdanning":48.4,"lekeOgOppholdsarealPerBarn":5.2,"andelBarnehagerSomOppfyllerPedagognormen":56.5,"andelBarnehagerSomIkkeOppfyllerPedagognormen":6.0,"andelBarnehagerSomOppfyllerPedagognormenMedDispensasjon":37.5},"kostpenger":112.0,"type":"Ordinær barnehage","pedagogiskProfil":null,"apningstidFra":"07:30","apningstidTil":"17:00","oppfyllerPedagognorm":"Oppfyller normen med dispensasjon fra utdanningskravet","totalAntallKvadratmeter":695.0,"urlTilSoknadOmBarnehageplass":"https://www.oslo.kommune.no/barnehage/soke-eller-bytte-barnehage/"}