{"id":"9b7b997a-07f6-4541-8cb7-be6ef99c0223","alder":"1 - 2","ansatte":{"antallFra":1,"antallTil":4},"eierform":"Privat","basilId":"53093","erAktiv":true,"erBarnehage":true,"erBarnehageEier":false,"erPrivatBarnehage":true,"fylke":{"fylkesnavn":"Oslo","fylkesnummer":"03"},"kommune":{"kommunenavn":"Oslo","kommunenummer":"0301"},"kontaktinformasjon":{"postAdresse":{"adresselinje":"Skovveien 4","postnr":"0257","poststed":"OSLO"},"besoksAdresse":{"adresselinje":"Grankollveien 6","postnr":"0672","poststed":"OSLO"},"epost":"","url":"","telefon":""},"koordinatLatLng":[59.9123,10.86081],"malform":{"malformType":"B","malformNavn":"Bokmål"},"opprettetDato":"3/10/2011","navn":"Mummidalen Familiebarnehage Sima Haghelahi Avdeling Lille My","orgnr":"996689298","nsrId":"1014271","indikatorDataBarnehage":{"antallBarn":4,"antallBarnPerAnsatt":null,"andelAnsatteMedBarneOgUngdomsarbeiderfag":null,"andelAnsatteMedAnnenPedagogiskUtdanning":null,"andelAnsatteBarnehagelarer":null,"andelAnsatteMedAnnenBakgrunn":null,"andelAnsatteMedPedagogiskUtdanning":null,"lekeOgOppholdsarealPerBarn":null},"indikatorDataKommune":{"antallBarn":null,"antallBarnPerAnsatt":6.0,"andelAnsatteMedBarneOgUngdomsarbeiderfag":7.9,"andelAnsatteMedAnnenPedagogiskUtdanning":6.9,"andelAnsatteBarnehagelarer":34.9,"andelAnsatteMedAnnenBakgrunn":50.2,"andelAnsatteMedPedagogiskUtdanning":41.9,"lekeOgOppholdsarealPerBarn":5.2},"kostpenger":100.0,"type":"Familiebarnehage","pedagogiskProfil":"","apningstidFra":"08:00","apningstidTil":"16:30","oppfyllerPedagognorm":"","urlTilSoknadOmBarnehageplass":"https://www.oslo.kommune.no/barnehage/soke-eller-bytte-barnehage/"}