{"id":"02ae428e-abd6-44e3-af79-8a00c488bc0d","alder":"1 - 5","ansatte":{"antallFra":15,"antallTil":19},"eierform":"Privat","basilId":"48036","erAktiv":true,"erBarnehage":true,"erBarnehageEier":false,"erPrivatBarnehage":true,"fylke":{"fylkesnavn":"Telemark","fylkesnummer":"08"},"kommune":{"kommunenavn":"Skien","kommunenummer":"0806"},"kontaktinformasjon":{"postAdresse":{"adresselinje":"Vestre Einaren 5","postnr":"3744","poststed":"SKIEN"},"besoksAdresse":{"adresselinje":"Vestre Einaren 5","postnr":"3744","poststed":"SKIEN"},"epost":"einaren.barnehage@live.no","url":"http://www.einaren.barnehage.skien.no","telefon":"35 53 83 66"},"koordinatLatLng":[59.2095,9.557604],"malform":{"malformType":"B","malformNavn":"Bokmål"},"opprettetDato":"4/1/1990","navn":"Einaren barnehage","orgnr":"972211095","nsrId":"1019902","indikatorDataBarnehage":{"antallBarn":49,"antallBarnPerAnsatt":6.6,"andelAnsatteMedBarneOgUngdomsarbeiderfag":9.1,"andelAnsatteMedAnnenPedagogiskUtdanning":null,"andelAnsatteBarnehagelarer":45.5,"andelAnsatteMedAnnenBakgrunn":45.5,"andelAnsatteMedPedagogiskUtdanning":null,"lekeOgOppholdsarealPerBarn":4.9,"andelBarnehagerSomOppfyllerPedagognormen":null,"andelBarnehagerSomIkkeOppfyllerPedagognormen":null,"andelBarnehagerSomOppfyllerPedagognormenMedDispensasjon":null},"indikatorDataKommune":{"antallBarn":2651,"antallBarnPerAnsatt":6.4,"andelAnsatteMedBarneOgUngdomsarbeiderfag":19.3,"andelAnsatteMedAnnenPedagogiskUtdanning":null,"andelAnsatteBarnehagelarer":47.6,"andelAnsatteMedAnnenBakgrunn":33.1,"andelAnsatteMedPedagogiskUtdanning":null,"lekeOgOppholdsarealPerBarn":5.0,"andelBarnehagerSomOppfyllerPedagognormen":90.9,"andelBarnehagerSomIkkeOppfyllerPedagognormen":9.1,"andelBarnehagerSomOppfyllerPedagognormenMedDispensasjon":0.0},"kostpenger":275.0,"type":"Ordinær barnehage","pedagogiskProfil":null,"apningstidFra":"07:15","apningstidTil":"16:30","oppfyllerPedagognorm":"Oppfyller normen","totalAntallKvadratmeter":240.0,"urlTilSoknadOmBarnehageplass":"http://www.skien.kommune.no/Tjenester-A-A/Barn-og-familie/Barnehage/Barnehageplass/#"}