{"id":"1b096c44-f109-4964-b7c1-41a857b9b34b","alder":"1 - 5","ansatte":{"antallFra":35,"antallTil":39},"eierform":"Annet","basilId":"47152","erAktiv":true,"erBarnehage":true,"erBarnehageEier":false,"erPrivatBarnehage":true,"fylke":{"fylkesnavn":"Akershus","fylkesnummer":"02"},"kommune":{"kommunenavn":"Lørenskog","kommunenummer":"0230"},"kontaktinformasjon":{"postAdresse":{"adresselinje":"","postnr":"1478","poststed":"LØRENSKOG"},"besoksAdresse":{"adresselinje":"Nordbyhagaveien 35","postnr":"1474","poststed":"NORDBYHAGEN"},"epost":"magnar.johan.rori@ahus.no","url":"","telefon":""},"koordinatLatLng":[59.9309,10.9911],"malform":{"malformType":"B","malformNavn":"Bokmål"},"opprettetDato":"1/1/2003","navn":"Ahus - barnehage 2","orgnr":"986383670","nsrId":"1012954","indikatorDataBarnehage":{"antallBarn":54,"antallBarnPerAnsatt":6.1,"andelAnsatteMedBarneOgUngdomsarbeiderfag":46.2,"andelAnsatteMedAnnenPedagogiskUtdanning":0.0,"andelAnsatteBarnehagelarer":30.8,"andelAnsatteMedAnnenBakgrunn":23.1,"andelAnsatteMedPedagogiskUtdanning":30.8,"lekeOgOppholdsarealPerBarn":4.8,"andelBarnehagerSomOppfyllerPedagognormen":null,"andelBarnehagerSomIkkeOppfyllerPedagognormen":null,"andelBarnehagerSomOppfyllerPedagognormenMedDispensasjon":null},"indikatorDataKommune":{"antallBarn":2034,"antallBarnPerAnsatt":6.2,"andelAnsatteMedBarneOgUngdomsarbeiderfag":21.3,"andelAnsatteMedAnnenPedagogiskUtdanning":7.5,"andelAnsatteBarnehagelarer":38.5,"andelAnsatteMedAnnenBakgrunn":32.7,"andelAnsatteMedPedagogiskUtdanning":46.0,"lekeOgOppholdsarealPerBarn":5.2,"andelBarnehagerSomOppfyllerPedagognormen":63.6,"andelBarnehagerSomIkkeOppfyllerPedagognormen":6.1,"andelBarnehagerSomOppfyllerPedagognormenMedDispensasjon":30.3},"kostpenger":250.0,"type":"Ordinær barnehage","pedagogiskProfil":null,"apningstidFra":"06:45","apningstidTil":"17:00","oppfyllerPedagognorm":"Oppfyller ikke normen","totalAntallKvadratmeter":261.0,"urlTilSoknadOmBarnehageplass":"https://www.lorenskog.kommune.no/tjenester/barn-og-familie/barnehage/#"}