{"id":"73d1c7fc-b969-4013-8bf3-5dfbd79970fd","alder":"1 - 5","ansatte":{"antallFra":30,"antallTil":34},"eierform":"Kommunal","basilId":"49924","erAktiv":true,"erBarnehage":true,"erBarnehageEier":false,"erPrivatBarnehage":false,"fylke":{"fylkesnavn":"Sør-Trøndelag","fylkesnummer":"16"},"kommune":{"kommunenavn":"Rissa","kommunenummer":"1624"},"kontaktinformasjon":{"postAdresse":{"adresselinje":"","postnr":"7105","poststed":"STADSBYGD"},"besoksAdresse":{"adresselinje":"","postnr":"7105","poststed":"STADSBYGD"},"epost":"bente.butli@rissa.kommune.no","url":"","telefon":""},"koordinatLatLng":[63.4973,10.0145],"malform":{"malformType":"B","malformNavn":"Bokmål"},"opprettetDato":"1/1/1989","navn":"Fembøringen barnehage","orgnr":"974022877","nsrId":"1016114","indikatorDataBarnehage":{"antallBarn":74,"antallBarnPerAnsatt":5.9,"andelAnsatteMedBarneOgUngdomsarbeiderfag":40.0,"andelAnsatteMedAnnenPedagogiskUtdanning":null,"andelAnsatteBarnehagelarer":35.0,"andelAnsatteMedAnnenBakgrunn":25.0,"andelAnsatteMedPedagogiskUtdanning":null,"lekeOgOppholdsarealPerBarn":6.0,"andelBarnehagerSomOppfyllerPedagognormen":null,"andelBarnehagerSomIkkeOppfyllerPedagognormen":null,"andelBarnehagerSomOppfyllerPedagognormenMedDispensasjon":null},"indikatorDataKommune":{"antallBarn":308,"antallBarnPerAnsatt":5.7,"andelAnsatteMedBarneOgUngdomsarbeiderfag":33.0,"andelAnsatteMedAnnenPedagogiskUtdanning":null,"andelAnsatteBarnehagelarer":41.8,"andelAnsatteMedAnnenBakgrunn":25.3,"andelAnsatteMedPedagogiskUtdanning":null,"lekeOgOppholdsarealPerBarn":6.6,"andelBarnehagerSomOppfyllerPedagognormen":40.0,"andelBarnehagerSomIkkeOppfyllerPedagognormen":60.0,"andelBarnehagerSomOppfyllerPedagognormenMedDispensasjon":0.0},"kostpenger":270.0,"type":"Ordinær barnehage","pedagogiskProfil":["Språkbarnehage","Miljøbarnehage"],"apningstidFra":"06:45","apningstidTil":"16:45","oppfyllerPedagognorm":"Oppfyller ikke normen","totalAntallKvadratmeter":446.8,"urlTilSoknadOmBarnehageplass":"https://www.rissa.kommune.no/tjenester/barn-og-skole/barnehage/"}