{"id":"53e9c469-f71d-41fe-a4ee-25867fe08289","alder":"1 - 5","ansatte":{"antallFra":5,"antallTil":9},"eierform":"Privat","basilId":"58608","erAktiv":true,"erBarnehage":true,"erBarnehageEier":false,"erPrivatBarnehage":true,"fylke":{"fylkesnavn":"Aust-Agder","fylkesnummer":"09"},"kommune":{"kommunenavn":"Birkenes","kommunenummer":"0928"},"kontaktinformasjon":{"postAdresse":{"adresselinje":"Postboks 36","postnr":"4795","poststed":"BIRKELAND"},"besoksAdresse":{"adresselinje":"Humlegardsheia 27","postnr":"4766","poststed":"HEREFOSS"},"epost":"dl.birkenes@bhg.no","url":"","telefon":""},"koordinatLatLng":[58.52444,8.351111],"malform":{"malformType":"B","malformNavn":"Bokmål"},"opprettetDato":"7/1/2012","navn":"Birkenes Fus barnehage AS Avd Herefoss","orgnr":"913626826","nsrId":"1025460","indikatorDataBarnehage":{"antallBarn":29,"antallBarnPerAnsatt":6.8,"andelAnsatteMedBarneOgUngdomsarbeiderfag":0.0,"andelAnsatteMedAnnenPedagogiskUtdanning":0.0,"andelAnsatteBarnehagelarer":50.0,"andelAnsatteMedAnnenBakgrunn":50.0,"andelAnsatteMedPedagogiskUtdanning":50.0,"lekeOgOppholdsarealPerBarn":6.7,"andelBarnehagerSomOppfyllerPedagognormen":null,"andelBarnehagerSomIkkeOppfyllerPedagognormen":null,"andelBarnehagerSomOppfyllerPedagognormenMedDispensasjon":null},"indikatorDataKommune":{"antallBarn":339,"antallBarnPerAnsatt":6.0,"andelAnsatteMedBarneOgUngdomsarbeiderfag":14.0,"andelAnsatteMedAnnenPedagogiskUtdanning":3.0,"andelAnsatteBarnehagelarer":38.0,"andelAnsatteMedAnnenBakgrunn":45.0,"andelAnsatteMedPedagogiskUtdanning":41.0,"lekeOgOppholdsarealPerBarn":5.7,"andelBarnehagerSomOppfyllerPedagognormen":57.1,"andelBarnehagerSomIkkeOppfyllerPedagognormen":42.9,"andelBarnehagerSomOppfyllerPedagognormenMedDispensasjon":0.0},"kostpenger":350.0,"type":"Ordinær barnehage","pedagogiskProfil":null,"apningstidFra":"07:00","apningstidTil":"16:30","oppfyllerPedagognorm":"Oppfyller ikke normen","totalAntallKvadratmeter":193.0,"urlTilSoknadOmBarnehageplass":"http://www.birkenes.kommune.no/ressurser/TMCore/Temaord/Barnehage/#"}