{"id":"bb679d2f-ed51-4f15-9a14-68c8d1faae42","alder":"1 - 5","ansatte":{"antallFra":10,"antallTil":14},"eierform":"Privat","basilId":"49048","erAktiv":true,"erBarnehage":true,"erBarnehageEier":false,"erPrivatBarnehage":true,"fylke":{"fylkesnavn":"Nordland","fylkesnummer":"18"},"kommune":{"kommunenavn":"Narvik","kommunenummer":"1805"},"kontaktinformasjon":{"postAdresse":{"adresselinje":"Bjørkvangveien 2","postnr":"8530","poststed":"BJERKVIK"},"besoksAdresse":{"adresselinje":"Bjørkvangveien 2","postnr":"8530","poststed":"BJERKVIK"},"epost":"","url":"","telefon":"76 95 25 80"},"koordinatLatLng":[68.5568,17.56319],"malform":{"malformType":"B","malformNavn":"Bokmål"},"opprettetDato":"1/4/1994","navn":"Bjørkvang barnehage","orgnr":"973989677","nsrId":"1020245","indikatorDataBarnehage":{"antallBarn":28,"antallBarnPerAnsatt":6.1,"andelAnsatteMedBarneOgUngdomsarbeiderfag":14.3,"andelAnsatteMedAnnenPedagogiskUtdanning":0.0,"andelAnsatteBarnehagelarer":42.9,"andelAnsatteMedAnnenBakgrunn":42.9,"andelAnsatteMedPedagogiskUtdanning":42.9,"lekeOgOppholdsarealPerBarn":5.8},"indikatorDataKommune":{"antallBarn":977,"antallBarnPerAnsatt":5.9,"andelAnsatteMedBarneOgUngdomsarbeiderfag":22.0,"andelAnsatteMedAnnenPedagogiskUtdanning":3.9,"andelAnsatteBarnehagelarer":38.6,"andelAnsatteMedAnnenBakgrunn":35.4,"andelAnsatteMedPedagogiskUtdanning":42.5,"lekeOgOppholdsarealPerBarn":6.2},"kostpenger":250.0,"type":"Ordinær barnehage","pedagogiskProfil":"","apningstidFra":"06:45","apningstidTil":"16:30","oppfyllerPedagognorm":"Oppfyller ikke normen","urlTilSoknadOmBarnehageplass":"https://www.narvik.kommune.no/tjenester/barn-og-familie/barnehage/barnehageplass/#"}