{"id":"66b0fb6a-05d9-43c8-ab2b-3eb5ba7a5028","alder":"1 - 5","ansatte":{"antallFra":5,"antallTil":9},"eierform":"Kommunal","basilId":"49625","erAktiv":true,"erBarnehage":true,"erBarnehageEier":false,"erPrivatBarnehage":false,"fylke":{"fylkesnavn":"Aust-Agder","fylkesnummer":"09"},"kommune":{"kommunenavn":"Valle","kommunenummer":"0940"},"kontaktinformasjon":{"postAdresse":{"adresselinje":"","postnr":"4748","poststed":"RYSSTAD"},"besoksAdresse":{"adresselinje":"","postnr":"4748","poststed":"RYSSTAD"},"epost":"","url":"","telefon":"37 93 75 00"},"koordinatLatLng":[59.0934,7.5359],"malform":{"malformType":"B","malformNavn":"Bokmål"},"opprettetDato":"1/1/1989","navn":"Hylestad barnehage","orgnr":"875318012","nsrId":"1012556","indikatorDataBarnehage":{"antallBarn":13,"antallBarnPerAnsatt":3.8,"andelAnsatteMedBarneOgUngdomsarbeiderfag":33.3,"andelAnsatteMedAnnenPedagogiskUtdanning":0.0,"andelAnsatteBarnehagelarer":66.7,"andelAnsatteMedAnnenBakgrunn":0.0,"andelAnsatteMedPedagogiskUtdanning":66.7,"lekeOgOppholdsarealPerBarn":15.7,"andelBarnehagerSomOppfyllerPedagognormen":null,"andelBarnehagerSomIkkeOppfyllerPedagognormen":null,"andelBarnehagerSomOppfyllerPedagognormenMedDispensasjon":null},"indikatorDataKommune":{"antallBarn":43,"antallBarnPerAnsatt":3.9,"andelAnsatteMedBarneOgUngdomsarbeiderfag":38.9,"andelAnsatteMedAnnenPedagogiskUtdanning":5.6,"andelAnsatteBarnehagelarer":55.6,"andelAnsatteMedAnnenBakgrunn":0.0,"andelAnsatteMedPedagogiskUtdanning":61.1,"lekeOgOppholdsarealPerBarn":12.9,"andelBarnehagerSomOppfyllerPedagognormen":100.0,"andelBarnehagerSomIkkeOppfyllerPedagognormen":0.0,"andelBarnehagerSomOppfyllerPedagognormenMedDispensasjon":0.0},"kostpenger":400.0,"type":"Ordinær barnehage","pedagogiskProfil":null,"apningstidFra":"07:00","apningstidTil":"16:00","oppfyllerPedagognorm":"Oppfyller normen","totalAntallKvadratmeter":204.0,"urlTilSoknadOmBarnehageplass":"http://www.valle.kommune.no/barnehage.289938.nn.html#"}