{"Eier": "Frogn kommune", "nbrId": 1017482, "name": "Bilitt barnehage", "Eier_orgNr": 1003363}
{"Eier": "Bjerkeveien barnehage Sa", "nbrId": 1021095, "name": "Bjerkeveien barnehage Sa", "Eier_orgNr": 1013073}
{"Eier": "Frogn kommune", "nbrId": 1016962, "name": "Dal barnehage", "Eier_orgNr": 1003363}
{"Eier": "Dr\u00f8bak Montessori Stiftelse", "nbrId": 1020859, "name": "Dr\u00f8bak Montessoribarnehage", "Eier_orgNr": 1001091}
{"Eier": "Frogn kommune", "nbrId": 1013357, "name": "Dr\u00f8bak \u00c5pen barnehage", "Eier_orgNr": 1003363}
{"Eier": "Frogn kommune", "nbrId": 1015473, "name": "Dyrl\u00f8kke\u00e5sen barnehage", "Eier_orgNr": 1003363}
{"Eier": "Frogn kommune", "nbrId": 1017524, "name": "Elleflaten barnehage", "Eier_orgNr": 1003363}
{"Eier": "Frelsesarmeen", "nbrId": 1016766, "name": "Frelsesarmeens Barnehager Avd Solgry", "Eier_orgNr": 1001509}
{"Eier": "Sogstieika barnehage Sa", "nbrId": 1020276, "name": "Frogn Foreldrelagsbarnehage", "Eier_orgNr": 1012576}
{"Eier": "Frogn Pedagogiske Senter AS", "nbrId": 1022431, "name": "Frogn Pedagogiske Senter AS", "Eier_orgNr": 1019425}
{"Eier": "Gry Hultgren", "nbrId": 1021580, "name": "Frogn/dr\u00f8bak Natur og G\u00e5rdsbarnehage", "Eier_orgNr": 1025728}
{"Eier": "Hap Holding AS", "nbrId": 2000489, "name": "Hap Holding AS", "Eier_orgNr": 2000470}
{"Eier": "Frogn kommune", "nbrId": 1017525, "name": "Heer barnehage", "Eier_orgNr": 1003363}
{"Eier": "Heer Grendehus barnehage Sa", "nbrId": 1019860, "name": "Heer Grendehus barnehage Sa", "Eier_orgNr": 1014605}
{"Eier": "Lindebakken barnehage", "nbrId": 1019855, "name": "Lindebakken barnehage", "Eier_orgNr": 1025281}
{"Eier": "L\u00f8vspretten Familiebarnehage Brita B\u00e6ck", "nbrId": 1020705, "name": "L\u00f8vspretten Familiebarnehage", "Eier_orgNr": 1016262}
{"Eier": "Ole Brumm Familiebarnehage Nyg\u00e5rd", "nbrId": 1021008, "name": "Ole Brumm Familiebarnehage", "Eier_orgNr": 1012964}
{"Eier": "Tertitten barnehage Ans", "nbrId": 1020333, "name": "Tertitten barnehage Ans", "Eier_orgNr": 1014862}
{"Eier": "Frogn kommune", "nbrId": 1013919, "name": "Trollberget barnehage", "Eier_orgNr": 1003363}
{"Eier": "Frogn kommune", "nbrId": 1017526, "name": "Ullerud barnehage", "Eier_orgNr": 1003363}
