{"id":"58f47243-0256-4f53-ae4c-a90130e91af3","alder":"1 - 5","ansatte":{"antallFra":40,"antallTil":44},"eierform":"Privat","basilId":"52294","erAktiv":true,"erBarnehage":true,"erBarnehageEier":false,"erPrivatBarnehage":true,"fylke":{"fylkesnavn":"Nordland","fylkesnummer":"18"},"kommune":{"kommunenavn":"Alstahaug","kommunenummer":"1820"},"kontaktinformasjon":{"postAdresse":{"adresselinje":"Forshaugen 17","postnr":"8800","poststed":"SANDNESSJØEN"},"besoksAdresse":{"adresselinje":"Forshaugen 17","postnr":"8800","poststed":"SANDNESSJØEN"},"epost":"forshaugen@barnehage.no","url":"http://forshaugen.barnehage.no","telefon":"75 04 31 00"},"koordinatLatLng":[66.01003,12.6061],"malform":{"malformType":"B","malformNavn":"Bokmål"},"opprettetDato":"1/17/2008","navn":"Sandnessjøen barnehage AS","orgnr":"892328242","nsrId":"1021774","indikatorDataBarnehage":{"antallBarn":99,"antallBarnPerAnsatt":6.2,"andelAnsatteMedBarneOgUngdomsarbeiderfag":34.6,"andelAnsatteMedAnnenPedagogiskUtdanning":0.0,"andelAnsatteBarnehagelarer":34.6,"andelAnsatteMedAnnenBakgrunn":30.8,"andelAnsatteMedPedagogiskUtdanning":34.6,"lekeOgOppholdsarealPerBarn":6.9},"indikatorDataKommune":{"antallBarn":385,"antallBarnPerAnsatt":5.8,"andelAnsatteMedBarneOgUngdomsarbeiderfag":33.0,"andelAnsatteMedAnnenPedagogiskUtdanning":2.8,"andelAnsatteBarnehagelarer":40.6,"andelAnsatteMedAnnenBakgrunn":23.6,"andelAnsatteMedPedagogiskUtdanning":43.4,"lekeOgOppholdsarealPerBarn":6.7},"kostpenger":300.0,"type":"Ordinær barnehage","pedagogiskProfil":"Annet","apningstidFra":"06:30","apningstidTil":"17:00","oppfyllerPedagognorm":"Oppfyller normen med dispensasjon fra utdanningskravet","urlTilSoknadOmBarnehageplass":"http://www.alstahaug.kommune.no/barnehage.197261.no.html#"}