{"id":"9248db4a-53f6-4b17-9c97-15ba3d9e30f2","alder":"1 - 5","ansatte":{"antallFra":25,"antallTil":29},"eierform":"Privat","basilId":"52345","erAktiv":true,"erBarnehage":true,"erBarnehageEier":false,"erPrivatBarnehage":true,"fylke":{"fylkesnavn":"Nordland","fylkesnummer":"18"},"kommune":{"kommunenavn":"Bodø","kommunenummer":"1804"},"kontaktinformasjon":{"postAdresse":{"adresselinje":"Olav V gate 98B","postnr":"8004","poststed":"BODØ"},"besoksAdresse":{"adresselinje":"Styrmannsveien 10","postnr":"8070","poststed":"BODØ"},"epost":"roar@bv-as.no","url":"","telefon":""},"koordinatLatLng":[67.2711,14.4374],"malform":{"malformType":"B","malformNavn":"Bokmål"},"opprettetDato":"3/12/2008","navn":"Lille Frøbel barnehage Avd Bodøsjøveien","orgnr":"992624620","nsrId":"1018392","indikatorDataBarnehage":{"antallBarn":99,"antallBarnPerAnsatt":6.7,"andelAnsatteMedBarneOgUngdomsarbeiderfag":0.0,"andelAnsatteMedAnnenPedagogiskUtdanning":0.0,"andelAnsatteBarnehagelarer":42.9,"andelAnsatteMedAnnenBakgrunn":57.1,"andelAnsatteMedPedagogiskUtdanning":42.9,"lekeOgOppholdsarealPerBarn":4.5},"indikatorDataKommune":{"antallBarn":2937,"antallBarnPerAnsatt":6.6,"andelAnsatteMedBarneOgUngdomsarbeiderfag":12.3,"andelAnsatteMedAnnenPedagogiskUtdanning":2.6,"andelAnsatteBarnehagelarer":45.9,"andelAnsatteMedAnnenBakgrunn":39.2,"andelAnsatteMedPedagogiskUtdanning":48.5,"lekeOgOppholdsarealPerBarn":5.0},"kostpenger":295.0,"type":"Ordinær barnehage","pedagogiskProfil":"","apningstidFra":"06:45","apningstidTil":"16:45","oppfyllerPedagognorm":"Oppfyller normen","urlTilSoknadOmBarnehageplass":"http://bodo.kommune.no/soke-barnehageplass/category1966.html#"}