{"id":"f2377c0f-54d4-4432-8364-f948582d73c8","alder":"1 - 5","ansatte":{"antallFra":40,"antallTil":44},"eierform":"Privat","basilId":"48631","erAktiv":true,"erBarnehage":true,"erBarnehageEier":false,"erPrivatBarnehage":true,"fylke":{"fylkesnavn":"Hordaland","fylkesnummer":"12"},"kommune":{"kommunenavn":"Meland","kommunenummer":"1256"},"kontaktinformasjon":{"postAdresse":{"adresselinje":"Melandsvegen 38","postnr":"5918","poststed":"FREKHAUG"},"besoksAdresse":{"adresselinje":"Melandsvegen 38","postnr":"5918","poststed":"FREKHAUG"},"epost":"styrer.blaklokka@barnehage.no","url":"","telefon":"56 17 74 90"},"koordinatLatLng":[60.53365,5.15634],"malform":{"malformType":"N","malformNavn":"Nynorsk"},"opprettetDato":"1/1/1982","navn":"Blåklokka barnehage","orgnr":"973383469","nsrId":"1021577","indikatorDataBarnehage":{"antallBarn":111,"antallBarnPerAnsatt":5.6,"andelAnsatteMedBarneOgUngdomsarbeiderfag":6.5,"andelAnsatteMedAnnenPedagogiskUtdanning":null,"andelAnsatteBarnehagelarer":41.9,"andelAnsatteMedAnnenBakgrunn":51.6,"andelAnsatteMedPedagogiskUtdanning":null,"lekeOgOppholdsarealPerBarn":5.6,"andelBarnehagerSomOppfyllerPedagognormen":null,"andelBarnehagerSomIkkeOppfyllerPedagognormen":null,"andelBarnehagerSomOppfyllerPedagognormenMedDispensasjon":null},"indikatorDataKommune":{"antallBarn":601,"antallBarnPerAnsatt":6.0,"andelAnsatteMedBarneOgUngdomsarbeiderfag":6.3,"andelAnsatteMedAnnenPedagogiskUtdanning":null,"andelAnsatteBarnehagelarer":43.0,"andelAnsatteMedAnnenBakgrunn":50.6,"andelAnsatteMedPedagogiskUtdanning":null,"lekeOgOppholdsarealPerBarn":5.4,"andelBarnehagerSomOppfyllerPedagognormen":75.0,"andelBarnehagerSomIkkeOppfyllerPedagognormen":0.0,"andelBarnehagerSomOppfyllerPedagognormenMedDispensasjon":25.0},"kostpenger":300.0,"type":"Ordinær barnehage","pedagogiskProfil":["Tros- eller livssynsbarnehage"],"apningstidFra":"06:45","apningstidTil":"17:00","oppfyllerPedagognorm":"Oppfyller normen","totalAntallKvadratmeter":625.0,"urlTilSoknadOmBarnehageplass":"http://www.meland.kommune.no/barnehage.304792.nn.html#"}